flaskmysqlcloudcli.py
flaskmysqlcloudcli-0.2.0.dist-info/METADATA
flaskmysqlcloudcli-0.2.0.dist-info/WHEEL
flaskmysqlcloudcli-0.2.0.dist-info/RECORD
